gradle.properties
hexdoc_hexthings/__gradle_version__.py
hexdoc_hexthings/__init__.py
hexdoc_hexthings/__version__.py
hexdoc_hexthings/_hooks.py
hexdoc_hexthings/py.typed
hexdoc_hexthings/_export/.gitignore
hexdoc_hexthings/_export/__init__.py
hexdoc_hexthings/_export/generated/__init__.py
hexdoc_hexthings/_export/generated/hexthings.hexdoc.json
hexdoc_hexthings/_export/generated/hexthings.patterns.hexdoc.json
hexdoc_hexthings/_export/generated/assets/hexcasting/patchouli_books/thehexbook/en_us/entries/patterns/dict.json5
hexdoc_hexthings/_export/generated/assets/hexcasting/patchouli_books/thehexbook/en_us/entries/patterns/hexutils.json5
hexdoc_hexthings/_export/generated/assets/hexcasting/patchouli_books/thehexbook/en_us/entries/patterns/uiua.json5
hexdoc_hexthings/_export/generated/assets/hexthings/lang/en_us.flatten.json5
hexdoc_hexthings/_export/generated/assets/hexthings/lang/zh_cn.flatten.json5
hexdoc_hexthings/_templates/__init__.py
hexdoc_hexthings-0.1.6.1.1.20.1.1.2.dist-info/METADATA
hexdoc_hexthings-0.1.6.1.1.20.1.1.2.dist-info/WHEEL
hexdoc_hexthings-0.1.6.1.1.20.1.1.2.dist-info/entry_points.txt
hexdoc_hexthings-0.1.6.1.1.20.1.1.2.dist-info/licenses/LICENSE
hexdoc_hexthings-0.1.6.1.1.20.1.1.2.dist-info/RECORD
