Metadata-Version: 2.4
Name: hexdoc-hexthings
Version: 0.1.6.1.1.20.1.1.2
Summary: Some extra patterns I think would be neat
Project-URL: Homepage, https://real-septicake.github.io/HexThings
Project-URL: Source, https://github.com/Real-Septicake/HexThings
Author: Real-Septicake
License-File: LICENSE
Keywords: hexdoc
Requires-Python: >=3.12
Requires-Dist: hexdoc-hexcasting~=0.11.2.1.0
